lsst_versions/__init__.py
lsst_versions/__version__.py
lsst_versions/_cmd.py
lsst_versions/_versions.py
lsst_versions/hatch.py
lsst_versions/py.typed
lsst_versions-1.6.0.dist-info/LICENSE
lsst_versions-1.6.0.dist-info/METADATA
lsst_versions-1.6.0.dist-info/WHEEL
lsst_versions-1.6.0.dist-info/entry_points.txt
lsst_versions-1.6.0.dist-info/top_level.txt
lsst_versions-1.6.0.dist-info/RECORD
