Metadata-Version: 2.2
Name: lsst-versions
Version: 1.6.0
Summary: Calculate package versions following LSST code conventions.
Home-page: https://github.com/lsst/lsst_versions
Author: Rubin Observatory Data Management
Author-email: dm-admin@lists.lsst.org
Project-URL: Source code, https://github.com/lsst/lsst_versions
Project-URL: Issue tracker, https://github.com/lsst/lsst_versions/issues
Keywords: lsst
Classifier: Intended Audience :: Developers
Classifier: License :: OSI Approved :: BSD License
Classifier: Operating System :: OS Independent
Classifier: Programming Language :: Python :: 3
Classifier: Programming Language :: Python :: 3.8
Classifier: Programming Language :: Python :: 3.9
Classifier: Programming Language :: Python :: 3.10
Classifier: Programming Language :: Python :: 3.11
Classifier: Programming Language :: Python :: 3.12
Classifier: Topic :: Software Development :: Libraries
Classifier: Topic :: Software Development :: Version Control
Classifier: Topic :: System :: Software Distribution
Requires-Python: >=3.8
License-File: LICENSE
Requires-Dist: setuptools>=46.0
Requires-Dist: tomli>1.0.0
Requires-Dist: GitPython>=3.1
Requires-Dist: packaging
Provides-Extra: dev
Requires-Dist: pytest>=3.2; extra == "dev"
Requires-Dist: flake8>=3.7.5; extra == "dev"
Requires-Dist: pytest-cov>=5.0; extra == "dev"
Requires-Dist: pytest-flake8>=1.0.4; extra == "dev"
Requires-Dist: hatchling>=1.27.0; extra == "dev"
Provides-Extra: typing
Requires-Dist: mypy>=1.14; extra == "typing"
Requires-Dist: types-setuptools>=75; extra == "typing"
